gandi_tf/__init__.py
gandi_tf/main.py
gandi_2_terraform-1.3.3.dist-info/LICENSE
gandi_2_terraform-1.3.3.dist-info/METADATA
gandi_2_terraform-1.3.3.dist-info/WHEEL
gandi_2_terraform-1.3.3.dist-info/entry_points.txt
gandi_2_terraform-1.3.3.dist-info/RECORD
