Metadata-Version: 2.3
Name: gandi-2-terraform
Version: 1.3.3
Summary: CLI to read Gandi.net live DNS records and generate corresponding TF gandi_livedns_record resources
License: AGPL
Keywords: gandi,terraform,DNS
Author: Marc-Aurèle Brothier
Author-email: m@brothier.org
Requires-Python: >=3.8.1,<4.0
Classifier: License :: OSI Approved :: GNU Affero General Public License v3 or later (AGPLv3+)
Classifier: License :: Other/Proprietary License
Classifier: Programming Language :: Python :: 3
Classifier: Programming Language :: Python :: 3.9
Classifier: Programming Language :: Python :: 3.10
Classifier: Programming Language :: Python :: 3.11
Classifier: Programming Language :: Python :: 3.12
Classifier: Programming Language :: Python :: 3.13
Classifier: Programming Language :: Python :: 3.8
Classifier: Topic :: Internet :: Name Service (DNS)
Requires-Dist: click (>=8.0.3,<9.0.0)
Requires-Dist: requests (>=2.27.1,<3.0.0)
Project-URL: Bug Tracker, https://github.com/marcaurele/gandi-2-terraform/issues
Project-URL: Homepage, https://github.com/marcaurele/gandi-2-terraform
Project-URL: Repository, https://github.com/marcaurele/gandi-2-terraform
